osnma_core.py
auxiliar_data/exceptions.py
auxiliar_data/osnma_fields.py
auxiliar_data/osnma_structures.py
auxiliar_data/test_data.py
tests/kroot_verification.py
tests/pkr_verification.py
tests/tesla_verification.py
osnma_core-0.0.11.dist-info/LICENSE
osnma_core-0.0.11.dist-info/METADATA
osnma_core-0.0.11.dist-info/WHEEL
osnma_core-0.0.11.dist-info/top_level.txt
osnma_core-0.0.11.dist-info/RECORD
